py_graphs/__init__.py
graphypy-0.0.1.dist-info/LICENSE
graphypy-0.0.1.dist-info/METADATA
graphypy-0.0.1.dist-info/WHEEL
graphypy-0.0.1.dist-info/top_level.txt
graphypy-0.0.1.dist-info/RECORD
