Metadata-Version: 2.1
Name: graphypy
Version: 0.0.1
Summary: A python graph libary.
Author-email: Andreas Venturini <andreas.venturini@live.de>
Maintainer-email: Andreas Venturini <andreas.venturini@live.de>
License: MIT License
Project-URL: Homepage, https://github.com/Andiyi/graphypy
Project-URL: Bug Tracker, https://github.com/Andiyi/graphypy/issues
Keywords: graph,graphs,graph-theory,graph-algorithms
Classifier: Programming Language :: Python :: 3
Classifier: License :: OSI Approved :: MIT License
Classifier: Operating System :: OS Independent
Requires-Python: >=3.11
License-File: LICENSE
